reywechat/__init__.py
reywechat/rall.py
reywechat/rbase.py
reywechat/rcache.py
reywechat/rclient.py
reywechat/rdb.py
reywechat/rlog.py
reywechat/rreceive.py
reywechat/rsend.py
reywechat/rtrigger.py
reywechat/rwechat.py
reywechat/data/HPSocket4C.dll
reywechat/data/version.dll
reywechat-1.0.113.dist-info/METADATA
reywechat-1.0.113.dist-info/WHEEL
reywechat-1.0.113.dist-info/licenses/LICENSE
reywechat-1.0.113.dist-info/RECORD
