Metadata-Version: 2.4
Name: reywechat
Version: 1.0.113
Summary: WeChat client control method set.
Project-URL: homepage, https://github.com/reyxbo/reywechat/
Author-email: Rey <reyxbo@163.com>
License: Copyright 2025 ReyXBo
License-File: LICENSE
Keywords: helper,rey,reyxbo,robot,wechat
Requires-Python: >=3.12
Requires-Dist: beautifulsoup4
Requires-Dist: reydb
Requires-Dist: reykit
Requires-Dist: reyserver
